{
	"properties": {
		"prefix": "$",
		"suffix": ""
	},
	"rounds": [
		{
			"values": {
				"amounts": [200]
			},
			"categories": [
				{
					"name": "State Capitals",
					"clues": [
						{
							"answer": "Built in 1792, St. Joseph's Cathedral is the oldest church in this Louisiana capital",
							"correct": "What is Baton Rouge?"
						}
					]
				}
			]
		}
	],
	"final": {
		"category": "American Political Terms",
		"answer": "This phrase first appeared in 1845, followed by \"to overspread the continent alloted by providence\"",
		"correct": "What is \"Manifest Destiny\"?"
	}

}